CHANGES.txt
LICENSE.txt
MANIFEST.in
README.txt
distribute_setup.py
setup.cfg
setup.py
tox.ini
docs/Makefile
docs/source/api.rst
docs/source/changelog.rst
docs/source/conf.py
docs/source/index.rst
stsci/__init__.py
stsci.distutils.egg-info/PKG-INFO
stsci.distutils.egg-info/SOURCES.txt
stsci.distutils.egg-info/dependency_links.txt
stsci.distutils.egg-info/entry_points.txt
stsci.distutils.egg-info/namespace_packages.txt
stsci.distutils.egg-info/not-zip-safe
stsci.distutils.egg-info/requires.txt
stsci.distutils.egg-info/top_level.txt
stsci/distutils/__init__.py
stsci/distutils/astutils.py
stsci/distutils/hooks.py
stsci/distutils/release.py
stsci/distutils/svnutils.py
stsci/distutils/version.py
stsci/distutils/versionutils.py
stsci/distutils/command/__init__.py
stsci/distutils/command/build_optional_ext.py
stsci/distutils/command/easier_install.py
stsci/distutils/tests/__init__.py
stsci/distutils/tests/test_commands.py
stsci/distutils/tests/test_hooks.py
stsci/distutils/tests/util.py
stsci/distutils/tests/testpackage/CHANGES.txt
stsci/distutils/tests/testpackage/LICENSE.txt
stsci/distutils/tests/testpackage/MANIFEST.in
stsci/distutils/tests/testpackage/README.txt
stsci/distutils/tests/testpackage/distribute_setup.py
stsci/distutils/tests/testpackage/setup.cfg
stsci/distutils/tests/testpackage/setup.py
stsci/distutils/tests/testpackage/data_files/a.txt
stsci/distutils/tests/testpackage/data_files/b.txt
stsci/distutils/tests/testpackage/data_files/c.rst
stsci/distutils/tests/testpackage/src/testext.c
stsci/distutils/tests/testpackage/stsci/__init__.py
stsci/distutils/tests/testpackage/stsci/testpackage/__init__.py
stsci/distutils/tests/testpackage/stsci/testpackage/package_data/1.txt
stsci/distutils/tests/testpackage/stsci/testpackage/package_data/2.txt