Metadata-Version: 1.1
Name: stsci.distutils
Version: 0.3.6
Summary: distutils/packaging-related utilities used by some of STScI's packages
Home-page: http://www.stsci.edu/resources/software_hardware/stsci_python
Author: Erik M. Bray
Author-email: embray@stsci.edu
License: UNKNOWN
Platform: UNKNOWN
Classifier: Development Status :: 3 - Alpha
Classifier: Intended Audience :: Developers
Classifier: License :: OSI Approved :: BSD License
Classifier: Programming Language :: Python
Classifier: Topic :: Scientific/Engineering
Classifier: Topic :: Software Development :: Build Tools
Classifier: Topic :: Software Development :: Libraries :: Python Modules
Classifier: Topic :: System :: Archiving :: Packaging
